setup.py
android_webview.egg-info/PKG-INFO
android_webview.egg-info/SOURCES.txt
android_webview.egg-info/dependency_links.txt
android_webview.egg-info/entry_points.txt
android_webview.egg-info/top_level.txt
awebview/__init__.py
awebview/android_webview.py
awebview/templates/AndroidManifest.xml
awebview/templates/MainActivity.java
awebview/templates/strings.xml