Metadata-Version: 1.0
Name: android-webview
Version: 0.1.2
Summary: Python script to generate android webview based apps
Home-page: https://github.com/raelmax/android-webview
Author: Rael Max
Author-email: contato@raelmax.com
License: UNKNOWN
Platform: UNKNOWN
